pydantic_collection/__init__.py
pydantic_collection/version.py
pydantic_collection/aws/__init__.py
pydantic_collection/aws/apigateway/__init__.py
pydantic_collection/aws/apigateway/models.py
pydantic_collection/aws/lambda_/__init__.py
pydantic_collection/aws/lambda_/models.py
pydantic_collection/aws/lambda_/stubs.py
pydantic_collection/aws/sns/__init__.py
pydantic_collection/aws/sns/models.py
pydantic_collection/aws/sqs/__init__.py
pydantic_collection/aws/sqs/models.py
tests/__init__.py
tests/aws/__init__.py
tests/aws/apigateway/__init__.py
tests/aws/apigateway/test_models.py
tests/aws/lambda_/__init__.py
tests/aws/lambda_/test_models.py
tests/aws/sns/__init__.py
tests/aws/sns/test_models.py
tests/aws/sqs/__init__.py
tests/aws/sqs/test_models.py
pydantic_collection-0.0.3.dist-info/LICENSE
pydantic_collection-0.0.3.dist-info/METADATA
pydantic_collection-0.0.3.dist-info/WHEEL
pydantic_collection-0.0.3.dist-info/top_level.txt
pydantic_collection-0.0.3.dist-info/zip-safe
pydantic_collection-0.0.3.dist-info/RECORD
