Metadata-Version: 2.1
Name: pydantic-collection
Version: 0.0.3
Summary: pydantic-collection is collections of pydantic model
Home-page: https://github.com/koxudaxi/pydantic-collection
Author: Koudai Aono
Author-email: koxudaxi@gmail.com
License: UNKNOWN
Platform: UNKNOWN
Classifier: Development Status :: 3 - Alpha
Classifier: Natural Language :: English
Classifier: License :: OSI Approved :: MIT License
Classifier: Programming Language :: Python :: 3
Classifier: Programming Language :: Python :: 3.8
Classifier: Programming Language :: Python :: Implementation :: CPython
Requires-Python: >=3.8.0
Requires-Dist: pydantic (>=1.4)
Provides-Extra: all
Requires-Dist: pytest-runner ; extra == 'all'
Requires-Dist: setuptools-scm ; extra == 'all'
Requires-Dist: pytest ; extra == 'all'
Requires-Dist: pytest-cov ; extra == 'all'
Requires-Dist: pytest-mock ; extra == 'all'
Requires-Dist: mypy ; extra == 'all'
Requires-Dist: black ; extra == 'all'
Requires-Dist: isort ; extra == 'all'
Requires-Dist: mkdocs ; extra == 'all'
Requires-Dist: mkdocs-material ; extra == 'all'
Requires-Dist: wheel ; extra == 'all'
Requires-Dist: twine ; extra == 'all'
Requires-Dist: codecov ; extra == 'all'
Provides-Extra: ci
Requires-Dist: codecov ; extra == 'ci'
Provides-Extra: docs
Requires-Dist: mkdocs ; extra == 'docs'
Requires-Dist: mkdocs-material ; extra == 'docs'
Provides-Extra: setup
Requires-Dist: pytest-runner ; extra == 'setup'
Requires-Dist: setuptools-scm ; extra == 'setup'
Provides-Extra: test
Requires-Dist: pytest ; extra == 'test'
Requires-Dist: pytest-cov ; extra == 'test'
Requires-Dist: pytest-mock ; extra == 'test'
Requires-Dist: mypy ; extra == 'test'
Requires-Dist: black ; extra == 'test'
Requires-Dist: isort ; extra == 'test'
Provides-Extra: wheel
Requires-Dist: wheel ; extra == 'wheel'
Requires-Dist: twine ; extra == 'wheel'
